pwchem/__init__.py
pwchem/bibtex.py
pwchem/constants.py
pwchem/protocols.conf
pwchem/pwchem_logo.png
pwchem/version.py
pwchem/objects/__init__.py
pwchem/objects/base.py
pwchem/objects/reactions.py
pwchem/protocols/__init__.py
pwchem/protocols/Databases/protocol_ZINC_filter.py
pwchem/protocols/Databases/protocol_fetch_ligands.py
pwchem/protocols/Databases/protocol_import_setOfDatabaseIDs.py
pwchem/protocols/Databases/protocol_smallMol_identify.py
pwchem/protocols/Databases/protocol_uniprot_crossref.py
pwchem/protocols/General/protocol_add_attribute.py
pwchem/protocols/General/protocol_converter.py
pwchem/protocols/General/protocol_export_csv.py
pwchem/protocols/General/protocol_operate_libraries.py
pwchem/protocols/General/protocol_operate_set.py
pwchem/protocols/General/protocol_pymol.py
pwchem/protocols/General/protocol_ranx_fuse.py
pwchem/protocols/MolecularDynamics/protocol_parametrize_ligand.py
pwchem/protocols/Sequences/protocol_calculate_conservation.py
pwchem/protocols/Sequences/protocol_combineScores_sequence_roi.py
pwchem/protocols/Sequences/protocol_define_multiepitope.py
pwchem/protocols/Sequences/protocol_define_sequence_roi.py
pwchem/protocols/Sequences/protocol_define_sequences.py
pwchem/protocols/Sequences/protocol_extract_attribute_ROIs.py
pwchem/protocols/Sequences/protocol_generate_variants.py
pwchem/protocols/Sequences/protocol_import_sequence_roi.py
pwchem/protocols/Sequences/protocol_import_setOfSequences.py
pwchem/protocols/Sequences/protocol_import_variants.py
pwchem/protocols/Sequences/protocol_map_attribute_to_sequence_ROIs.py
pwchem/protocols/Sequences/protocol_map_sequence_structure_ROIs.py
pwchem/protocols/Sequences/protocol_modify_multiepitope.py
pwchem/protocols/Sequences/protocol_multipleSequence_alignment.py
pwchem/protocols/Sequences/protocol_operate_sequence_rois.py
pwchem/protocols/Sequences/protocol_optimize_multiepitope.py
pwchem/protocols/Sequences/protocol_pairWise_alignment.py
scipion_chem-1.0.1.dist-info/LICENSE
scipion_chem-1.0.1.dist-info/METADATA
scipion_chem-1.0.1.dist-info/WHEEL
scipion_chem-1.0.1.dist-info/entry_points.txt
scipion_chem-1.0.1.dist-info/top_level.txt
scipion_chem-1.0.1.dist-info/RECORD
