Metadata-Version: 2.1
Name: scipion-chem
Version: 1.0.1
Summary: Base Scipion plugin defining objects and protocols for CHEMoinformatics and Virtual Drug Screening.
Author-email: Daniel Del Hoyo <ddelhoyo@cnb.csic.es>, Martin Salinas <ssalinasmartin@gmail.com>, Carlos Oscar Sanchez Sorzano <coss@cnb.csic.es>
License: GNU General Public License v3 (GPLv3)
Project-URL: Homepage, https://github.com/scipion-chem/scipion-chem
Project-URL: Issues, https://github.com/scipion-chem/scipion-chem/issues
Keywords: scipion,pdb,scipion-3,drug,screening,chemoinformatics
Requires-Python: >=3.8
License-File: LICENSE
Requires-Dist: scipion-app
Requires-Dist: scipion-em
Requires-Dist: scipion-pyworkflow
Requires-Dist: lxml
Requires-Dist: scipy
Requires-Dist: parmed
Requires-Dist: scikit-learn
Requires-Dist: deap==1.4
Requires-Dist: pandas==2.0
